pygest/__init__.py
pygest/fields.py
pygest/manager.py
pygest/metadata.py
pygest/models.py
pygest-0.0.1.dist-info/LICENSE
pygest-0.0.1.dist-info/METADATA
pygest-0.0.1.dist-info/WHEEL
pygest-0.0.1.dist-info/top_level.txt
pygest-0.0.1.dist-info/RECORD
