Metadata-Version: 2.1
Name: pygest
Version: 0.0.1
Summary: A python framework for digesting APIs
Home-page: https://github.com/dog/pygest
Author: Dog
License: GNU General Public License v3 (GPLv3)
Platform: UNKNOWN
Classifier: Development Status :: 1 - Planning
Classifier: Programming Language :: Python :: 3
Classifier: Operating System :: OS Independent
Classifier: License :: OSI Approved :: GNU General Public License v3 (GPLv3)
License-File: LICENSE
Requires-Dist: httpx
